phalcopulse/__init__.py
phalcopulse/graphics/__init__.py
phalcopulse/graphics/mesh.py
phalcopulse/graphics/objects.py
phalcopulse/physics/__init__.py
phalcopulse/studio/__init__.py
phalcopulse/studio/application.py
phalcopulse/studio/camera.py
phalcopulse/studio/capture.py
phalcopulse/studio/scene.py
phalcopulse/studio/ui.py
phalcopulse/ui/__init__.py
phalcopulse/ui/drawing.py
phalcopulse/ui/manager.py
phalcopulse/ui/widgets.py
phalcopulse/utils/__init__.py
phalcopulse-0.1.5.dist-info/licenses/LICENSE
phalcopulse-0.1.5.dist-info/METADATA
phalcopulse-0.1.5.dist-info/WHEEL
phalcopulse-0.1.5.dist-info/top_level.txt
phalcopulse-0.1.5.dist-info/RECORD
