Metadata-Version: 2.4
Name: phalcopulse
Version: 0.1.5
Summary: A real-time 3D visualization engine with PyOpenGL.
Project-URL: Homepage, https://github.com/PhalcoAi/PhalcoPulse
Project-URL: Issues, https://github.com/PhalcoAi/PhalcoPulse/issues
License-File: LICENSE
Requires-Dist: pygame-ce>=2.3.1
Requires-Dist: PyOpenGL>=3.1.6
Requires-Dist: numpy>=1.20.0
Requires-Dist: pywavefront>=1.3.3
Requires-Dist: imageio>=2.20.0
Requires-Dist: imageio-ffmpeg>=0.4.7
Dynamic: license-file
